reinforcebotagent/__init__.py
reinforcebotagent/agent.py
reinforcebotagent/agent_profile.py
reinforcebotagent/replay_buffer.py
reinforcebotagent/reward.py
reinforcebotagent/trainer.py
reinforcebotagent-0.0.3.dist-info/METADATA
reinforcebotagent-0.0.3.dist-info/WHEEL
reinforcebotagent-0.0.3.dist-info/top_level.txt
reinforcebotagent-0.0.3.dist-info/RECORD
