Metadata-Version: 2.1
Name: reinforcebotagent
Version: 0.0.3
Summary: The ReinforceBot agent shared library
Home-page: https://github.com/novucs/project
Author: Will
Author-email: contact@novucs.net
License: UNKNOWN
Platform: UNKNOWN
Classifier: Programming Language :: Python :: 3
Classifier: License :: OSI Approved :: MIT License
Classifier: Operating System :: OS Independent
Requires-Python: >=3.6
